monitors/__init__.py
monitors/default.py
monitors/dynamic.py
monitors/monitor_pid.py
monitors/monitor_set.py
monitors/monitor_util.py
monitors/tradition.py
monitors/page/__init__.py
monitors/page/api.py
monitors/page/constants.py
monitors/page/core.py
monitors/page/hook.py
monitors/page/reporter.py
monitors/page/toolbox.py
monitors/page/video.py
monitors/page/classifier/__init__.py
monitors/page/classifier/base.py
monitors/page/classifier/keras.py
monitors/page/classifier/ssim.py
monitors/page/classifier/svm.py
monitors/page/cutter/__init__.py
monitors/page/cutter/cut_range.py
monitors/page/cutter/cut_result.py
monitors/page/cutter/cutter.py
monitors/page/template/report.html
monitors/page/template/summary_template.html
monitors-1.1.2.dist-info/LICENSE
monitors-1.1.2.dist-info/METADATA
monitors-1.1.2.dist-info/WHEEL
monitors-1.1.2.dist-info/top_level.txt
monitors-1.1.2.dist-info/RECORD
