Metadata-Version: 2.1
Name: monitors
Version: 1.1.2
Summary: monitor tools
Home-page: https://github.com/openutx
Author: lijiawei
Author-email: jiawei.li2@qq.com
License: MIT Licence
Keywords: grafana,monitors,process monitor,system monitor,influxdb
Platform: any
Classifier: License :: OSI Approved :: MIT License
Classifier: Development Status :: 5 - Production/Stable
Classifier: Environment :: Console :: Curses
Classifier: Operating System :: MacOS
Classifier: Operating System :: POSIX
Classifier: Operating System :: Microsoft :: Windows
Classifier: Programming Language :: Python :: 3 :: Only
Classifier: Programming Language :: Python :: 3.6
Classifier: Programming Language :: Python :: 3.7
Classifier: Programming Language :: Python :: 3.8
Classifier: Programming Language :: Python :: Implementation :: CPython
Classifier: Topic :: System :: Networking :: Monitoring
Classifier: Topic :: Software Development :: Testing
Classifier: Typing :: Typed
License-File: LICENSE
Requires-Dist: psutil
Requires-Dist: influxdb
Requires-Dist: requests
Requires-Dist: loguru
Requires-Dist: opencv-python (<4.5,>=4.1.2.30)
Requires-Dist: opencv-contrib-python (<4.5,>=4.1.2.30)
Requires-Dist: numpy (>=0.18.0)
Requires-Dist: loguru (>=0.2.5)
Requires-Dist: scikit-image (>=0.16.0)
Requires-Dist: scikit-learn (>=0.21.0)
Requires-Dist: pyecharts (>=1.3.1)
Requires-Dist: findit (>=0.5.8)
Requires-Dist: Jinja2 (>=2.10.1)
Requires-Dist: MarkupSafe (>=2.0.1)
Requires-Dist: fire (>=0.2.1)
Requires-Dist: keras (>=2.3.1)
Requires-Dist: pydantic (>=0.32.2)
